{"data":{"mdx":{"code":{"body":"function _extends() { _extends = Object.assign || function (target) { for (var i = 1; i < arguments.length; i++) { var source = arguments[i]; for (var key in source) { if (Object.prototype.hasOwnProperty.call(source, key)) { target[key] = source[key]; } } } return target; }; return _extends.apply(this, arguments); }\n\nfunction _objectWithoutProperties(source, excluded) { if (source == null) return {}; var target = _objectWithoutPropertiesLoose(source, excluded); var key, i; if (Object.getOwnPropertySymbols) { var sourceSymbolKeys = Object.getOwnPropertySymbols(source); for (i = 0; i < sourceSymbolKeys.length; i++) { key = sourceSymbolKeys[i]; if (excluded.indexOf(key) >= 0) continue; if (!Object.prototype.propertyIsEnumerable.call(source, key)) continue; target[key] = source[key]; } } return target; }\n\nfunction _objectWithoutPropertiesLoose(source, excluded) { if (source == null) return {}; var target = {}; var sourceKeys = Object.keys(source); var key, i; for (i = 0; i < sourceKeys.length; i++) { key = sourceKeys[i]; if (excluded.indexOf(key) >= 0) continue; target[key] = source[key]; } return target; }\n\n/* @jsx mdx */\nvar _frontmatter = {\n  \"path\": \"/get-started/accessibility-guide\"\n};\n\nvar makeShortcode = function makeShortcode(name) {\n  return function MDXDefaultShortcode(props) {\n    console.warn(\"Component \" + name + \" was not imported, exported, or provided by MDXProvider as global scope\");\n    return mdx(\"div\", props);\n  };\n};\n\nvar layoutProps = {\n  _frontmatter: _frontmatter\n};\nvar MDXLayout = \"wrapper\";\nreturn function MDXContent(_ref) {\n  var components = _ref.components,\n      props = _objectWithoutProperties(_ref, [\"components\"]);\n\n  return mdx(MDXLayout, _extends({}, layoutProps, props, {\n    components: components,\n    mdxType: \"MDXLayout\"\n  }), mdx(\"h1\", {\n    \"id\": \"accessibility-guide\"\n  }, mdx(\"a\", _extends({\n    parentName: \"h1\"\n  }, {\n    \"href\": \"#accessibility-guide\",\n    \"aria-label\": \"accessibility guide permalink\",\n    \"className\": \"anchor\"\n  }), mdx(\"svg\", _extends({\n    parentName: \"a\"\n  }, {\n    \"aria-hidden\": \"true\",\n    \"focusable\": \"false\",\n    \"height\": \"16\",\n    \"version\": \"1.1\",\n    \"viewBox\": \"0 0 16 16\",\n    \"width\": \"16\"\n  }), mdx(\"path\", _extends({\n    parentName: \"svg\"\n  }, {\n    \"fillRule\": \"evenodd\",\n    \"d\": \"M4 9h1v1H4c-1.5 0-3-1.69-3-3.5S2.55 3 4 3h4c1.45 0 3 1.69 3 3.5 0 1.41-.91 2.72-2 3.25V8.59c.58-.45 1-1.27 1-2.09C10 5.22 8.98 4 8 4H4c-.98 0-2 1.22-2 2.5S3 9 4 9zm9-3h-1v1h1c1 0 2 1.22 2 2.5S13.98 12 13 12H9c-.98 0-2-1.22-2-2.5 0-.83.42-1.64 1-2.09V6.25c-1.09.53-2 1.84-2 3.25C6 11.31 7.55 13 9 13h4c1.45 0 3-1.69 3-3.5S14.5 6 13 6z\"\n  })))), \"Accessibility Guide\"), mdx(\"p\", null, mdx(\"em\", {\n    parentName: \"p\"\n  }, \"Please note, this guide is a work in progress and will be updated regularly. We welcome your comments and feedback.\")), mdx(\"p\", null, \"The goal of software accessibility is to remove barriers and create inclusive product experiences that work for everyone, regardless of physical ability.\"), mdx(\"p\", null, \"Since accessibility is best achieved when considered early in the design and development process, we ask everyone who contributes to or consumes PatternFly to understand accessibility needs and how they can be met. The following guide provides techniques and suggestions to help you design, develop, and test UIs to ensure that everyone has a good user experience.\"), mdx(\"ul\", null, mdx(\"li\", {\n    parentName: \"ul\"\n  }, mdx(\"a\", _extends({\n    parentName: \"li\"\n  }, {\n    \"href\": \"#understanding-users-needs\"\n  }), \"Understanding Users\\u2019 Needs\")), mdx(\"li\", {\n    parentName: \"ul\"\n  }, mdx(\"a\", _extends({\n    parentName: \"li\"\n  }, {\n    \"href\": \"#designing-and-developing-for-accessibility\"\n  }), \"Designing and Developing for Accessibility\")), mdx(\"li\", {\n    parentName: \"ul\"\n  }, mdx(\"a\", _extends({\n    parentName: \"li\"\n  }, {\n    \"href\": \"#checklists\"\n  }), \"Checklists\"), mdx(\"ul\", {\n    parentName: \"li\"\n  }, mdx(\"li\", {\n    parentName: \"ul\"\n  }, mdx(\"a\", _extends({\n    parentName: \"li\"\n  }, {\n    \"href\": \"#what-patternfly-should-address\"\n  }), \"What PatternFly Should Address\")), mdx(\"li\", {\n    parentName: \"ul\"\n  }, mdx(\"a\", _extends({\n    parentName: \"li\"\n  }, {\n    \"href\": \"#what-products-should-address\"\n  }), \"What Products Should Address\")))), mdx(\"li\", {\n    parentName: \"ul\"\n  }, mdx(\"a\", _extends({\n    parentName: \"li\"\n  }, {\n    \"href\": \"#guidelines-and-references\"\n  }), \"Guidelines and References\")), mdx(\"li\", {\n    parentName: \"ul\"\n  }, mdx(\"a\", _extends({\n    parentName: \"li\"\n  }, {\n    \"href\": \"#techniques\"\n  }), \"Techniques\")), mdx(\"li\", {\n    parentName: \"ul\"\n  }, mdx(\"a\", _extends({\n    parentName: \"li\"\n  }, {\n    \"href\": \"#testing\"\n  }), \"Testing\"))), mdx(\"h2\", {\n    \"id\": \"understanding-users-needs\"\n  }, mdx(\"a\", _extends({\n    parentName: \"h2\"\n  }, {\n    \"href\": \"#understanding-users-needs\",\n    \"aria-label\": \"understanding users needs permalink\",\n    \"className\": \"anchor\"\n  }), mdx(\"svg\", _extends({\n    parentName: \"a\"\n  }, {\n    \"aria-hidden\": \"true\",\n    \"focusable\": \"false\",\n    \"height\": \"16\",\n    \"version\": \"1.1\",\n    \"viewBox\": \"0 0 16 16\",\n    \"width\": \"16\"\n  }), mdx(\"path\", _extends({\n    parentName: \"svg\"\n  }, {\n    \"fillRule\": \"evenodd\",\n    \"d\": \"M4 9h1v1H4c-1.5 0-3-1.69-3-3.5S2.55 3 4 3h4c1.45 0 3 1.69 3 3.5 0 1.41-.91 2.72-2 3.25V8.59c.58-.45 1-1.27 1-2.09C10 5.22 8.98 4 8 4H4c-.98 0-2 1.22-2 2.5S3 9 4 9zm9-3h-1v1h1c1 0 2 1.22 2 2.5S13.98 12 13 12H9c-.98 0-2-1.22-2-2.5 0-.83.42-1.64 1-2.09V6.25c-1.09.53-2 1.84-2 3.25C6 11.31 7.55 13 9 13h4c1.45 0 3-1.69 3-3.5S14.5 6 13 6z\"\n  })))), \"Understanding Users\\u2019 Needs\"), mdx(\"p\", null, \"Great user experiences don\\u2019t just happen; they\\u2019re designed, tested, and refined with the user in mind. To develop inclusive products, it\\u2019s important to understand the varying needs of a wide range of users and consider the assistive tools and methods they use. This section provides information to help you better understand and address the needs of these \", mdx(\"a\", _extends({\n    parentName: \"p\"\n  }, {\n    \"href\": \"https://a11yproject.com/posts/myth-accessibility-is-blind-people/\"\n  }), \"different user groups\"), \".\"), mdx(\"p\", null, \"Note: It\\u2019s possible for a user to fall into more than one group, or to use tools and devices designed for a different user group. One of the greatest benefits of an inclusive design practice is that methods designed for a specific user group will often provide benefits to everyone.\"), mdx(\"h3\", {\n    \"id\": \"no-vision\"\n  }, mdx(\"a\", _extends({\n    parentName: \"h3\"\n  }, {\n    \"href\": \"#no-vision\",\n    \"aria-label\": \"no vision permalink\",\n    \"className\": \"anchor\"\n  }), mdx(\"svg\", _extends({\n    parentName: \"a\"\n  }, {\n    \"aria-hidden\": \"true\",\n    \"focusable\": \"false\",\n    \"height\": \"16\",\n    \"version\": \"1.1\",\n    \"viewBox\": \"0 0 16 16\",\n    \"width\": \"16\"\n  }), mdx(\"path\", _extends({\n    parentName: \"svg\"\n  }, {\n    \"fillRule\": \"evenodd\",\n    \"d\": \"M4 9h1v1H4c-1.5 0-3-1.69-3-3.5S2.55 3 4 3h4c1.45 0 3 1.69 3 3.5 0 1.41-.91 2.72-2 3.25V8.59c.58-.45 1-1.27 1-2.09C10 5.22 8.98 4 8 4H4c-.98 0-2 1.22-2 2.5S3 9 4 9zm9-3h-1v1h1c1 0 2 1.22 2 2.5S13.98 12 13 12H9c-.98 0-2-1.22-2-2.5 0-.83.42-1.64 1-2.09V6.25c-1.09.53-2 1.84-2 3.25C6 11.31 7.55 13 9 13h4c1.45 0 3-1.69 3-3.5S14.5 6 13 6z\"\n  })))), \"No Vision\"), mdx(\"p\", null, \"Users with no vision rely on screen readers to access web sites and applications. Often, screen reader users will navigate a page by browsing specific elements, like headers, links, or form elements. Use semantic elements and check that labels are meaningful when pulled out of context.\"), mdx(\"h3\", {\n    \"id\": \"low-vision\"\n  }, mdx(\"a\", _extends({\n    parentName: \"h3\"\n  }, {\n    \"href\": \"#low-vision\",\n    \"aria-label\": \"low vision permalink\",\n    \"className\": \"anchor\"\n  }), mdx(\"svg\", _extends({\n    parentName: \"a\"\n  }, {\n    \"aria-hidden\": \"true\",\n    \"focusable\": \"false\",\n    \"height\": \"16\",\n    \"version\": \"1.1\",\n    \"viewBox\": \"0 0 16 16\",\n    \"width\": \"16\"\n  }), mdx(\"path\", _extends({\n    parentName: \"svg\"\n  }, {\n    \"fillRule\": \"evenodd\",\n    \"d\": \"M4 9h1v1H4c-1.5 0-3-1.69-3-3.5S2.55 3 4 3h4c1.45 0 3 1.69 3 3.5 0 1.41-.91 2.72-2 3.25V8.59c.58-.45 1-1.27 1-2.09C10 5.22 8.98 4 8 4H4c-.98 0-2 1.22-2 2.5S3 9 4 9zm9-3h-1v1h1c1 0 2 1.22 2 2.5S13.98 12 13 12H9c-.98 0-2-1.22-2-2.5 0-.83.42-1.64 1-2.09V6.25c-1.09.53-2 1.84-2 3.25C6 11.31 7.55 13 9 13h4c1.45 0 3-1.69 3-3.5S14.5 6 13 6z\"\n  })))), \"Low Vision\"), mdx(\"p\", null, \"Users with low vision can have different needs depending on the nature of their visual impairment. Users may have difficulty with color differentiation, blurriness, or lack of vision in central or peripheral areas. These needs mean that interfaces should not rely on color to communicate information, palettes need to have sufficient contrast, and layouts should be responsive when font sizes are increased.\"), mdx(\"h3\", {\n    \"id\": \"motor\"\n  }, mdx(\"a\", _extends({\n    parentName: \"h3\"\n  }, {\n    \"href\": \"#motor\",\n    \"aria-label\": \"motor permalink\",\n    \"className\": \"anchor\"\n  }), mdx(\"svg\", _extends({\n    parentName: \"a\"\n  }, {\n    \"aria-hidden\": \"true\",\n    \"focusable\": \"false\",\n    \"height\": \"16\",\n    \"version\": \"1.1\",\n    \"viewBox\": \"0 0 16 16\",\n    \"width\": \"16\"\n  }), mdx(\"path\", _extends({\n    parentName: \"svg\"\n  }, {\n    \"fillRule\": \"evenodd\",\n    \"d\": \"M4 9h1v1H4c-1.5 0-3-1.69-3-3.5S2.55 3 4 3h4c1.45 0 3 1.69 3 3.5 0 1.41-.91 2.72-2 3.25V8.59c.58-.45 1-1.27 1-2.09C10 5.22 8.98 4 8 4H4c-.98 0-2 1.22-2 2.5S3 9 4 9zm9-3h-1v1h1c1 0 2 1.22 2 2.5S13.98 12 13 12H9c-.98 0-2-1.22-2-2.5 0-.83.42-1.64 1-2.09V6.25c-1.09.53-2 1.84-2 3.25C6 11.31 7.55 13 9 13h4c1.45 0 3-1.69 3-3.5S14.5 6 13 6z\"\n  })))), \"Motor\"), mdx(\"p\", null, \"Users with poor motor control can use a range of devices to access contents. Users who rely on a keyboard need elements that are keyboard accessible and highly visible when in focus. Users who rely on a mouse or touch need target areas that are large enough to be hit easily.\"), mdx(\"h3\", {\n    \"id\": \"cognitive\"\n  }, mdx(\"a\", _extends({\n    parentName: \"h3\"\n  }, {\n    \"href\": \"#cognitive\",\n    \"aria-label\": \"cognitive permalink\",\n    \"className\": \"anchor\"\n  }), mdx(\"svg\", _extends({\n    parentName: \"a\"\n  }, {\n    \"aria-hidden\": \"true\",\n    \"focusable\": \"false\",\n    \"height\": \"16\",\n    \"version\": \"1.1\",\n    \"viewBox\": \"0 0 16 16\",\n    \"width\": \"16\"\n  }), mdx(\"path\", _extends({\n    parentName: \"svg\"\n  }, {\n    \"fillRule\": \"evenodd\",\n    \"d\": \"M4 9h1v1H4c-1.5 0-3-1.69-3-3.5S2.55 3 4 3h4c1.45 0 3 1.69 3 3.5 0 1.41-.91 2.72-2 3.25V8.59c.58-.45 1-1.27 1-2.09C10 5.22 8.98 4 8 4H4c-.98 0-2 1.22-2 2.5S3 9 4 9zm9-3h-1v1h1c1 0 2 1.22 2 2.5S13.98 12 13 12H9c-.98 0-2-1.22-2-2.5 0-.83.42-1.64 1-2.09V6.25c-1.09.53-2 1.84-2 3.25C6 11.31 7.55 13 9 13h4c1.45 0 3-1.69 3-3.5S14.5 6 13 6z\"\n  })))), \"Cognitive\"), mdx(\"p\", null, \"Users who have difficulty processing information benefit from well-written content. Information should clear, concise, and easy to scan. Consider visual hierarchy, chunk content into short, related sections, and avoid long paragraphs.\"), mdx(\"h2\", {\n    \"id\": \"designing-and-developing-for-accessibility\"\n  }, mdx(\"a\", _extends({\n    parentName: \"h2\"\n  }, {\n    \"href\": \"#designing-and-developing-for-accessibility\",\n    \"aria-label\": \"designing and developing for accessibility permalink\",\n    \"className\": \"anchor\"\n  }), mdx(\"svg\", _extends({\n    parentName: \"a\"\n  }, {\n    \"aria-hidden\": \"true\",\n    \"focusable\": \"false\",\n    \"height\": \"16\",\n    \"version\": \"1.1\",\n    \"viewBox\": \"0 0 16 16\",\n    \"width\": \"16\"\n  }), mdx(\"path\", _extends({\n    parentName: \"svg\"\n  }, {\n    \"fillRule\": \"evenodd\",\n    \"d\": \"M4 9h1v1H4c-1.5 0-3-1.69-3-3.5S2.55 3 4 3h4c1.45 0 3 1.69 3 3.5 0 1.41-.91 2.72-2 3.25V8.59c.58-.45 1-1.27 1-2.09C10 5.22 8.98 4 8 4H4c-.98 0-2 1.22-2 2.5S3 9 4 9zm9-3h-1v1h1c1 0 2 1.22 2 2.5S13.98 12 13 12H9c-.98 0-2-1.22-2-2.5 0-.83.42-1.64 1-2.09V6.25c-1.09.53-2 1.84-2 3.25C6 11.31 7.55 13 9 13h4c1.45 0 3-1.69 3-3.5S14.5 6 13 6z\"\n  })))), \"Designing and Developing for Accessibility\"), mdx(\"p\", null, \"Our goal is to meet \", mdx(\"a\", _extends({\n    parentName: \"p\"\n  }, {\n    \"href\": \"https://www.w3.org/WAI/WCAG21/quickref/?currentsidebar=%23col_customize&levels=aaa\"\n  }), \"level AA in the Web Content Accessibility Guidelines 2.1\"), \". To help you get started, the following sections break some of these down by area of focus.\"), mdx(\"h2\", {\n    \"id\": \"checklists\"\n  }, mdx(\"a\", _extends({\n    parentName: \"h2\"\n  }, {\n    \"href\": \"#checklists\",\n    \"aria-label\": \"checklists permalink\",\n    \"className\": \"anchor\"\n  }), mdx(\"svg\", _extends({\n    parentName: \"a\"\n  }, {\n    \"aria-hidden\": \"true\",\n    \"focusable\": \"false\",\n    \"height\": \"16\",\n    \"version\": \"1.1\",\n    \"viewBox\": \"0 0 16 16\",\n    \"width\": \"16\"\n  }), mdx(\"path\", _extends({\n    parentName: \"svg\"\n  }, {\n    \"fillRule\": \"evenodd\",\n    \"d\": \"M4 9h1v1H4c-1.5 0-3-1.69-3-3.5S2.55 3 4 3h4c1.45 0 3 1.69 3 3.5 0 1.41-.91 2.72-2 3.25V8.59c.58-.45 1-1.27 1-2.09C10 5.22 8.98 4 8 4H4c-.98 0-2 1.22-2 2.5S3 9 4 9zm9-3h-1v1h1c1 0 2 1.22 2 2.5S13.98 12 13 12H9c-.98 0-2-1.22-2-2.5 0-.83.42-1.64 1-2.09V6.25c-1.09.53-2 1.84-2 3.25C6 11.31 7.55 13 9 13h4c1.45 0 3-1.69 3-3.5S14.5 6 13 6z\"\n  })))), \"Checklists\"), mdx(\"h3\", {\n    \"id\": \"what-patternfly-should-address\"\n  }, mdx(\"a\", _extends({\n    parentName: \"h3\"\n  }, {\n    \"href\": \"#what-patternfly-should-address\",\n    \"aria-label\": \"what patternfly should address permalink\",\n    \"className\": \"anchor\"\n  }), mdx(\"svg\", _extends({\n    parentName: \"a\"\n  }, {\n    \"aria-hidden\": \"true\",\n    \"focusable\": \"false\",\n    \"height\": \"16\",\n    \"version\": \"1.1\",\n    \"viewBox\": \"0 0 16 16\",\n    \"width\": \"16\"\n  }), mdx(\"path\", _extends({\n    parentName: \"svg\"\n  }, {\n    \"fillRule\": \"evenodd\",\n    \"d\": \"M4 9h1v1H4c-1.5 0-3-1.69-3-3.5S2.55 3 4 3h4c1.45 0 3 1.69 3 3.5 0 1.41-.91 2.72-2 3.25V8.59c.58-.45 1-1.27 1-2.09C10 5.22 8.98 4 8 4H4c-.98 0-2 1.22-2 2.5S3 9 4 9zm9-3h-1v1h1c1 0 2 1.22 2 2.5S13.98 12 13 12H9c-.98 0-2-1.22-2-2.5 0-.83.42-1.64 1-2.09V6.25c-1.09.53-2 1.84-2 3.25C6 11.31 7.55 13 9 13h4c1.45 0 3-1.69 3-3.5S14.5 6 13 6z\"\n  })))), \"What PatternFly Should Address\"), mdx(\"p\", null, \"If you use PatternFly, or contribute to PatternFly as a designer or developer, these are the items that are expected to be covered in PatternFly:\"), mdx(\"table\", null, mdx(\"thead\", {\n    parentName: \"table\"\n  }, mdx(\"tr\", {\n    parentName: \"thead\"\n  }, mdx(\"th\", _extends({\n    parentName: \"tr\"\n  }, {\n    \"align\": null\n  }), \"Guideline\"), mdx(\"th\", _extends({\n    parentName: \"tr\"\n  }, {\n    \"align\": null\n  }), \"Link\"), mdx(\"th\", _extends({\n    parentName: \"tr\"\n  }, {\n    \"align\": null\n  })), mdx(\"th\", _extends({\n    parentName: \"tr\"\n  }, {\n    \"align\": null\n  })), mdx(\"th\", _extends({\n    parentName: \"tr\"\n  }, {\n    \"align\": null\n  })), mdx(\"th\", _extends({\n    parentName: \"tr\"\n  }, {\n    \"align\": null\n  })))), mdx(\"tbody\", {\n    parentName: \"table\"\n  }, mdx(\"tr\", {\n    parentName: \"tbody\"\n  }, mdx(\"td\", _extends({\n    parentName: \"tr\"\n  }, {\n    \"align\": null\n  }), \"Semantic html structures are used to accurately communicate purpose and relationship of UI elements\"), mdx(\"td\", _extends({\n    parentName: \"tr\"\n  }, {\n    \"align\": null\n  }), mdx(\"a\", _extends({\n    parentName: \"td\"\n  }, {\n    \"href\": \"https://www.w3.org/WAI/WCAG21/quickref/#info-and-relationships\"\n  }), \"WCAG 1.3.1\")), mdx(\"td\", _extends({\n    parentName: \"tr\"\n  }, {\n    \"align\": null\n  }), mdx(\"inlineCode\", {\n    parentName: \"td\"\n  }, \"design\")), mdx(\"td\", _extends({\n    parentName: \"tr\"\n  }, {\n    \"align\": null\n  }), mdx(\"inlineCode\", {\n    parentName: \"td\"\n  }, \"html\")), mdx(\"td\", _extends({\n    parentName: \"tr\"\n  }, {\n    \"align\": null\n  }), mdx(\"inlineCode\", {\n    parentName: \"td\"\n  }, \"css\")), mdx(\"td\", _extends({\n    parentName: \"tr\"\n  }, {\n    \"align\": null\n  }))), mdx(\"tr\", {\n    parentName: \"tbody\"\n  }, mdx(\"td\", _extends({\n    parentName: \"tr\"\n  }, {\n    \"align\": null\n  }), \"Color is not the only method of communication. Providing meaning through color is supplementary to providing meaning with text\"), mdx(\"td\", _extends({\n    parentName: \"tr\"\n  }, {\n    \"align\": null\n  }), mdx(\"a\", _extends({\n    parentName: \"td\"\n  }, {\n    \"href\": \"https://www.w3.org/WAI/WCAG21/quickref/#use-of-color\"\n  }), \"WCAG 1.4.1\")), mdx(\"td\", _extends({\n    parentName: \"tr\"\n  }, {\n    \"align\": null\n  }), mdx(\"inlineCode\", {\n    parentName: \"td\"\n  }, \"design\")), mdx(\"td\", _extends({\n    parentName: \"tr\"\n  }, {\n    \"align\": null\n  }), mdx(\"inlineCode\", {\n    parentName: \"td\"\n  }, \"html\")), mdx(\"td\", _extends({\n    parentName: \"tr\"\n  }, {\n    \"align\": null\n  }), mdx(\"inlineCode\", {\n    parentName: \"td\"\n  }, \"css\")), mdx(\"td\", _extends({\n    parentName: \"tr\"\n  }, {\n    \"align\": null\n  }))), mdx(\"tr\", {\n    parentName: \"tbody\"\n  }, mdx(\"td\", _extends({\n    parentName: \"tr\"\n  }, {\n    \"align\": null\n  }), \"Colors used provide sufficient contrast\"), mdx(\"td\", _extends({\n    parentName: \"tr\"\n  }, {\n    \"align\": null\n  }), mdx(\"a\", _extends({\n    parentName: \"td\"\n  }, {\n    \"href\": \"https://www.w3.org/WAI/WCAG21/quickref/#contrast-minimum\"\n  }), \"WCAG 1.4.3\"), \" and \", mdx(\"a\", _extends({\n    parentName: \"td\"\n  }, {\n    \"href\": \"https://www.w3.org/WAI/WCAG21/quickref/#non-text-contrast\"\n  }), \"1.4.11\")), mdx(\"td\", _extends({\n    parentName: \"tr\"\n  }, {\n    \"align\": null\n  })), mdx(\"td\", _extends({\n    parentName: \"tr\"\n  }, {\n    \"align\": null\n  })), mdx(\"td\", _extends({\n    parentName: \"tr\"\n  }, {\n    \"align\": null\n  }), mdx(\"inlineCode\", {\n    parentName: \"td\"\n  }, \"css\")), mdx(\"td\", _extends({\n    parentName: \"tr\"\n  }, {\n    \"align\": null\n  }))), mdx(\"tr\", {\n    parentName: \"tbody\"\n  }, mdx(\"td\", _extends({\n    parentName: \"tr\"\n  }, {\n    \"align\": null\n  }), \"Font sizes can scale up to 200% without loss of content or functionality, and up to 400% without needing to scroll in more than one direction.\"), mdx(\"td\", _extends({\n    parentName: \"tr\"\n  }, {\n    \"align\": null\n  }), mdx(\"a\", _extends({\n    parentName: \"td\"\n  }, {\n    \"href\": \"https://www.w3.org/WAI/WCAG21/quickref/#resize-text\"\n  }), \"WCAG\", \"\\xA0\", \"1.4.4\"), \" and \", mdx(\"a\", _extends({\n    parentName: \"td\"\n  }, {\n    \"href\": \"https://www.w3.org/WAI/WCAG21/quickref/#reflow\"\n  }), \"1.4.10\")), mdx(\"td\", _extends({\n    parentName: \"tr\"\n  }, {\n    \"align\": null\n  })), mdx(\"td\", _extends({\n    parentName: \"tr\"\n  }, {\n    \"align\": null\n  })), mdx(\"td\", _extends({\n    parentName: \"tr\"\n  }, {\n    \"align\": null\n  }), mdx(\"inlineCode\", {\n    parentName: \"td\"\n  }, \"css\")), mdx(\"td\", _extends({\n    parentName: \"tr\"\n  }, {\n    \"align\": null\n  }))), mdx(\"tr\", {\n    parentName: \"tbody\"\n  }, mdx(\"td\", _extends({\n    parentName: \"tr\"\n  }, {\n    \"align\": null\n  }), \"Styles that affect text spacing (line height, space between paragraphs, letter spacing, and word spacing) can be increased without loss of content or functionality\"), mdx(\"td\", _extends({\n    parentName: \"tr\"\n  }, {\n    \"align\": null\n  }), mdx(\"a\", _extends({\n    parentName: \"td\"\n  }, {\n    \"href\": \"https://www.w3.org/WAI/WCAG21/quickref/#text-spacing\"\n  }), \"WCAG 1.4.12\")), mdx(\"td\", _extends({\n    parentName: \"tr\"\n  }, {\n    \"align\": null\n  })), mdx(\"td\", _extends({\n    parentName: \"tr\"\n  }, {\n    \"align\": null\n  })), mdx(\"td\", _extends({\n    parentName: \"tr\"\n  }, {\n    \"align\": null\n  }), mdx(\"inlineCode\", {\n    parentName: \"td\"\n  }, \"css\")), mdx(\"td\", _extends({\n    parentName: \"tr\"\n  }, {\n    \"align\": null\n  }))), mdx(\"tr\", {\n    parentName: \"tbody\"\n  }, mdx(\"td\", _extends({\n    parentName: \"tr\"\n  }, {\n    \"align\": null\n  }), \"Contents that appear on hover and focus are dismissable, hoverable, and persistent\"), mdx(\"td\", _extends({\n    parentName: \"tr\"\n  }, {\n    \"align\": null\n  }), mdx(\"a\", _extends({\n    parentName: \"td\"\n  }, {\n    \"href\": \"https://www.w3.org/WAI/WCAG21/quickref/#content-on-hover-or-focus\"\n  }), \"WCAG 1.4.13\")), mdx(\"td\", _extends({\n    parentName: \"tr\"\n  }, {\n    \"align\": null\n  })), mdx(\"td\", _extends({\n    parentName: \"tr\"\n  }, {\n    \"align\": null\n  }), mdx(\"inlineCode\", {\n    parentName: \"td\"\n  }, \"html\")), mdx(\"td\", _extends({\n    parentName: \"tr\"\n  }, {\n    \"align\": null\n  }), mdx(\"inlineCode\", {\n    parentName: \"td\"\n  }, \"css\")), mdx(\"td\", _extends({\n    parentName: \"tr\"\n  }, {\n    \"align\": null\n  }), mdx(\"inlineCode\", {\n    parentName: \"td\"\n  }, \"js\"))), mdx(\"tr\", {\n    parentName: \"tbody\"\n  }, mdx(\"td\", _extends({\n    parentName: \"tr\"\n  }, {\n    \"align\": null\n  }), \"All functionality is keyboard accessible\"), mdx(\"td\", _extends({\n    parentName: \"tr\"\n  }, {\n    \"align\": null\n  }), mdx(\"a\", _extends({\n    parentName: \"td\"\n  }, {\n    \"href\": \"https://www.w3.org/WAI/WCAG21/quickref/#keyboard\"\n  }), \"WCAG 2.1.1\"), \" and \", mdx(\"a\", _extends({\n    parentName: \"td\"\n  }, {\n    \"href\": \"https://www.w3.org/WAI/WCAG21/quickref/#no-keyboard-trap\"\n  }), \"2.1.2\")), mdx(\"td\", _extends({\n    parentName: \"tr\"\n  }, {\n    \"align\": null\n  })), mdx(\"td\", _extends({\n    parentName: \"tr\"\n  }, {\n    \"align\": null\n  }), mdx(\"inlineCode\", {\n    parentName: \"td\"\n  }, \"html\")), mdx(\"td\", _extends({\n    parentName: \"tr\"\n  }, {\n    \"align\": null\n  })), mdx(\"td\", _extends({\n    parentName: \"tr\"\n  }, {\n    \"align\": null\n  }))), mdx(\"tr\", {\n    parentName: \"tbody\"\n  }, mdx(\"td\", _extends({\n    parentName: \"tr\"\n  }, {\n    \"align\": null\n  }), \"Order of elements in the HTML and in the layout follow a logical order\"), mdx(\"td\", _extends({\n    parentName: \"tr\"\n  }, {\n    \"align\": null\n  }), mdx(\"a\", _extends({\n    parentName: \"td\"\n  }, {\n    \"href\": \"https://www.w3.org/WAI/WCAG21/quickref/#meaningful-sequence\"\n  }), \"WCAG 1.3.2\"), \" and \", mdx(\"a\", _extends({\n    parentName: \"td\"\n  }, {\n    \"href\": \"https://www.w3.org/WAI/WCAG21/quickref/#focus-order\"\n  }), \"2.4.3\")), mdx(\"td\", _extends({\n    parentName: \"tr\"\n  }, {\n    \"align\": null\n  }), mdx(\"inlineCode\", {\n    parentName: \"td\"\n  }, \"design\")), mdx(\"td\", _extends({\n    parentName: \"tr\"\n  }, {\n    \"align\": null\n  }), mdx(\"inlineCode\", {\n    parentName: \"td\"\n  }, \"html\")), mdx(\"td\", _extends({\n    parentName: \"tr\"\n  }, {\n    \"align\": null\n  }), mdx(\"inlineCode\", {\n    parentName: \"td\"\n  }, \"css\")), mdx(\"td\", _extends({\n    parentName: \"tr\"\n  }, {\n    \"align\": null\n  }))), mdx(\"tr\", {\n    parentName: \"tbody\"\n  }, mdx(\"td\", _extends({\n    parentName: \"tr\"\n  }, {\n    \"align\": null\n  }), \"Elements with focus are clearly visible\"), mdx(\"td\", _extends({\n    parentName: \"tr\"\n  }, {\n    \"align\": null\n  }), mdx(\"a\", _extends({\n    parentName: \"td\"\n  }, {\n    \"href\": \"https://www.w3.org/WAI/WCAG21/quickref/#focus-visible\"\n  }), \"WCAG 2.4.7\")), mdx(\"td\", _extends({\n    parentName: \"tr\"\n  }, {\n    \"align\": null\n  })), mdx(\"td\", _extends({\n    parentName: \"tr\"\n  }, {\n    \"align\": null\n  })), mdx(\"td\", _extends({\n    parentName: \"tr\"\n  }, {\n    \"align\": null\n  }), mdx(\"inlineCode\", {\n    parentName: \"td\"\n  }, \"css\")), mdx(\"td\", _extends({\n    parentName: \"tr\"\n  }, {\n    \"align\": null\n  }))), mdx(\"tr\", {\n    parentName: \"tbody\"\n  }, mdx(\"td\", _extends({\n    parentName: \"tr\"\n  }, {\n    \"align\": null\n  }), \"Flashing content\"), mdx(\"td\", _extends({\n    parentName: \"tr\"\n  }, {\n    \"align\": null\n  }), mdx(\"a\", _extends({\n    parentName: \"td\"\n  }, {\n    \"href\": \"https://www.w3.org/WAI/WCAG21/quickref/?showtechniques=231#three-flashes-or-below-threshold\"\n  }), \"WCAG 2.3.1\")), mdx(\"td\", _extends({\n    parentName: \"tr\"\n  }, {\n    \"align\": null\n  })), mdx(\"td\", _extends({\n    parentName: \"tr\"\n  }, {\n    \"align\": null\n  })), mdx(\"td\", _extends({\n    parentName: \"tr\"\n  }, {\n    \"align\": null\n  }), mdx(\"inlineCode\", {\n    parentName: \"td\"\n  }, \"css\")), mdx(\"td\", _extends({\n    parentName: \"tr\"\n  }, {\n    \"align\": null\n  }))), mdx(\"tr\", {\n    parentName: \"tbody\"\n  }, mdx(\"td\", _extends({\n    parentName: \"tr\"\n  }, {\n    \"align\": null\n  }), \"Functionality that uses complex gestures can also be operated with a single pointer without a path based gesture\"), mdx(\"td\", _extends({\n    parentName: \"tr\"\n  }, {\n    \"align\": null\n  }), mdx(\"a\", _extends({\n    parentName: \"td\"\n  }, {\n    \"href\": \"https://www.w3.org/WAI/WCAG21/quickref/#pointer-gestures\"\n  }), \"WCAG 2.5.1\")), mdx(\"td\", _extends({\n    parentName: \"tr\"\n  }, {\n    \"align\": null\n  }), mdx(\"inlineCode\", {\n    parentName: \"td\"\n  }, \"design\")), mdx(\"td\", _extends({\n    parentName: \"tr\"\n  }, {\n    \"align\": null\n  })), mdx(\"td\", _extends({\n    parentName: \"tr\"\n  }, {\n    \"align\": null\n  })), mdx(\"td\", _extends({\n    parentName: \"tr\"\n  }, {\n    \"align\": null\n  }))), mdx(\"tr\", {\n    parentName: \"tbody\"\n  }, mdx(\"td\", _extends({\n    parentName: \"tr\"\n  }, {\n    \"align\": null\n  }), \"Pointer events can be cancelled\"), mdx(\"td\", _extends({\n    parentName: \"tr\"\n  }, {\n    \"align\": null\n  }), mdx(\"a\", _extends({\n    parentName: \"td\"\n  }, {\n    \"href\": \"https://www.w3.org/WAI/WCAG21/quickref/#pointer-cancellation\"\n  }), \"WCAG 2.5.2\")), mdx(\"td\", _extends({\n    parentName: \"tr\"\n  }, {\n    \"align\": null\n  })), mdx(\"td\", _extends({\n    parentName: \"tr\"\n  }, {\n    \"align\": null\n  })), mdx(\"td\", _extends({\n    parentName: \"tr\"\n  }, {\n    \"align\": null\n  })), mdx(\"td\", _extends({\n    parentName: \"tr\"\n  }, {\n    \"align\": null\n  }), mdx(\"inlineCode\", {\n    parentName: \"td\"\n  }, \"js\"))), mdx(\"tr\", {\n    parentName: \"tbody\"\n  }, mdx(\"td\", _extends({\n    parentName: \"tr\"\n  }, {\n    \"align\": null\n  }), \"Visible labels of UI components are either the same as the accessible name or used in the beginning of the accessible name\"), mdx(\"td\", _extends({\n    parentName: \"tr\"\n  }, {\n    \"align\": null\n  }), mdx(\"a\", _extends({\n    parentName: \"td\"\n  }, {\n    \"href\": \"https://www.w3.org/WAI/WCAG21/quickref/#label-in-name\"\n  }), \"WCAG 2.5.3\")), mdx(\"td\", _extends({\n    parentName: \"tr\"\n  }, {\n    \"align\": null\n  })), mdx(\"td\", _extends({\n    parentName: \"tr\"\n  }, {\n    \"align\": null\n  }), mdx(\"inlineCode\", {\n    parentName: \"td\"\n  }, \"html\")), mdx(\"td\", _extends({\n    parentName: \"tr\"\n  }, {\n    \"align\": null\n  })), mdx(\"td\", _extends({\n    parentName: \"tr\"\n  }, {\n    \"align\": null\n  }))), mdx(\"tr\", {\n    parentName: \"tbody\"\n  }, mdx(\"td\", _extends({\n    parentName: \"tr\"\n  }, {\n    \"align\": null\n  }), \"The target area for clickable elements is at least 44 by 44 \", mdx(\"a\", _extends({\n    parentName: \"td\"\n  }, {\n    \"href\": \"https://www.w3.org/TR/WCAG21/#dfn-css-pixels\"\n  }), \"CSS pixels\")), mdx(\"td\", _extends({\n    parentName: \"tr\"\n  }, {\n    \"align\": null\n  }), mdx(\"a\", _extends({\n    parentName: \"td\"\n  }, {\n    \"href\": \"https://www.w3.org/WAI/WCAG21/quickref/#target-size\"\n  }), \"WCAG 2.5.5 (AAA)\"), \"*\"), mdx(\"td\", _extends({\n    parentName: \"tr\"\n  }, {\n    \"align\": null\n  })), mdx(\"td\", _extends({\n    parentName: \"tr\"\n  }, {\n    \"align\": null\n  })), mdx(\"td\", _extends({\n    parentName: \"tr\"\n  }, {\n    \"align\": null\n  }), mdx(\"inlineCode\", {\n    parentName: \"td\"\n  }, \"css\")), mdx(\"td\", _extends({\n    parentName: \"tr\"\n  }, {\n    \"align\": null\n  }))), mdx(\"tr\", {\n    parentName: \"tbody\"\n  }, mdx(\"td\", _extends({\n    parentName: \"tr\"\n  }, {\n    \"align\": null\n  }), \"An accessible name is provided for all elements\"), mdx(\"td\", _extends({\n    parentName: \"tr\"\n  }, {\n    \"align\": null\n  }), mdx(\"a\", _extends({\n    parentName: \"td\"\n  }, {\n    \"href\": \"https://www.w3.org/WAI/WCAG21/quickref/#name-role-value\"\n  }), \"WCAG 4.1.2\")), mdx(\"td\", _extends({\n    parentName: \"tr\"\n  }, {\n    \"align\": null\n  }), mdx(\"inlineCode\", {\n    parentName: \"td\"\n  }, \"design\")), mdx(\"td\", _extends({\n    parentName: \"tr\"\n  }, {\n    \"align\": null\n  }), mdx(\"inlineCode\", {\n    parentName: \"td\"\n  }, \"html\")), mdx(\"td\", _extends({\n    parentName: \"tr\"\n  }, {\n    \"align\": null\n  })), mdx(\"td\", _extends({\n    parentName: \"tr\"\n  }, {\n    \"align\": null\n  }))), mdx(\"tr\", {\n    parentName: \"tbody\"\n  }, mdx(\"td\", _extends({\n    parentName: \"tr\"\n  }, {\n    \"align\": null\n  }), \"Status messages can be programmatically determined through role or properties\"), mdx(\"td\", _extends({\n    parentName: \"tr\"\n  }, {\n    \"align\": null\n  }), mdx(\"a\", _extends({\n    parentName: \"td\"\n  }, {\n    \"href\": \"https://www.w3.org/WAI/WCAG21/quickref/#status-messages\"\n  }), \"WCAG 4.1.3\")), mdx(\"td\", _extends({\n    parentName: \"tr\"\n  }, {\n    \"align\": null\n  })), mdx(\"td\", _extends({\n    parentName: \"tr\"\n  }, {\n    \"align\": null\n  }), mdx(\"inlineCode\", {\n    parentName: \"td\"\n  }, \"html\")), mdx(\"td\", _extends({\n    parentName: \"tr\"\n  }, {\n    \"align\": null\n  })), mdx(\"td\", _extends({\n    parentName: \"tr\"\n  }, {\n    \"align\": null\n  }))))), mdx(\"p\", null, \"*WCAG 2.5.5 is included for reference only. This guideline suggests a size that is larger than what PatternFly requires.\"), mdx(\"h3\", {\n    \"id\": \"what-products-should-address\"\n  }, mdx(\"a\", _extends({\n    parentName: \"h3\"\n  }, {\n    \"href\": \"#what-products-should-address\",\n    \"aria-label\": \"what products should address permalink\",\n    \"className\": \"anchor\"\n  }), mdx(\"svg\", _extends({\n    parentName: \"a\"\n  }, {\n    \"aria-hidden\": \"true\",\n    \"focusable\": \"false\",\n    \"height\": \"16\",\n    \"version\": \"1.1\",\n    \"viewBox\": \"0 0 16 16\",\n    \"width\": \"16\"\n  }), mdx(\"path\", _extends({\n    parentName: \"svg\"\n  }, {\n    \"fillRule\": \"evenodd\",\n    \"d\": \"M4 9h1v1H4c-1.5 0-3-1.69-3-3.5S2.55 3 4 3h4c1.45 0 3 1.69 3 3.5 0 1.41-.91 2.72-2 3.25V8.59c.58-.45 1-1.27 1-2.09C10 5.22 8.98 4 8 4H4c-.98 0-2 1.22-2 2.5S3 9 4 9zm9-3h-1v1h1c1 0 2 1.22 2 2.5S13.98 12 13 12H9c-.98 0-2-1.22-2-2.5 0-.83.42-1.64 1-2.09V6.25c-1.09.53-2 1.84-2 3.25C6 11.31 7.55 13 9 13h4c1.45 0 3-1.69 3-3.5S14.5 6 13 6z\"\n  })))), \"What Products Should Address\"), mdx(\"p\", null, \"If you consume PatternFly in your product, these are the items that are outside the scope of PatternFly, and should be addressed by the product developers and designers:\"), mdx(\"table\", null, mdx(\"thead\", {\n    parentName: \"table\"\n  }, mdx(\"tr\", {\n    parentName: \"thead\"\n  }, mdx(\"th\", _extends({\n    parentName: \"tr\"\n  }, {\n    \"align\": null\n  }), \"Guideline\"), mdx(\"th\", _extends({\n    parentName: \"tr\"\n  }, {\n    \"align\": null\n  }), \"Link\"), mdx(\"th\", _extends({\n    parentName: \"tr\"\n  }, {\n    \"align\": null\n  })), mdx(\"th\", _extends({\n    parentName: \"tr\"\n  }, {\n    \"align\": null\n  })))), mdx(\"tbody\", {\n    parentName: \"table\"\n  }, mdx(\"tr\", {\n    parentName: \"tbody\"\n  }, mdx(\"td\", _extends({\n    parentName: \"tr\"\n  }, {\n    \"align\": null\n  }), \"Skip to Main links\"), mdx(\"td\", _extends({\n    parentName: \"tr\"\n  }, {\n    \"align\": null\n  }), mdx(\"a\", _extends({\n    parentName: \"td\"\n  }, {\n    \"href\": \"https://www.w3.org/WAI/WCAG21/quickref/#bypass-blocks\"\n  }), \"WCAG 2.4.1\")), mdx(\"td\", _extends({\n    parentName: \"tr\"\n  }, {\n    \"align\": null\n  })), mdx(\"td\", _extends({\n    parentName: \"tr\"\n  }, {\n    \"align\": null\n  }), mdx(\"inlineCode\", {\n    parentName: \"td\"\n  }, \"development\"))), mdx(\"tr\", {\n    parentName: \"tbody\"\n  }, mdx(\"td\", _extends({\n    parentName: \"tr\"\n  }, {\n    \"align\": null\n  }), \"Page Titles\"), mdx(\"td\", _extends({\n    parentName: \"tr\"\n  }, {\n    \"align\": null\n  }), mdx(\"a\", _extends({\n    parentName: \"td\"\n  }, {\n    \"href\": \"https://www.w3.org/WAI/WCAG21/quickref/#page-titled\"\n  }), \"WCAG 2.4.2\")), mdx(\"td\", _extends({\n    parentName: \"tr\"\n  }, {\n    \"align\": null\n  })), mdx(\"td\", _extends({\n    parentName: \"tr\"\n  }, {\n    \"align\": null\n  }), mdx(\"inlineCode\", {\n    parentName: \"td\"\n  }, \"development\"))), mdx(\"tr\", {\n    parentName: \"tbody\"\n  }, mdx(\"td\", _extends({\n    parentName: \"tr\"\n  }, {\n    \"align\": null\n  }), \"Links \\u2014 If more than one link has the same label, it should also have the same url. Screen reader users can access the list of links that are on a page, which pulls the links out of context. If you have links with different URLs but the same label, then add additional text to provide context to the screen reader user.\"), mdx(\"td\", _extends({\n    parentName: \"tr\"\n  }, {\n    \"align\": null\n  }), mdx(\"a\", _extends({\n    parentName: \"td\"\n  }, {\n    \"href\": \"https://www.w3.org/WAI/WCAG21/quickref/#link-purpose-in-context\"\n  }), \"WCAG\", \"\\xA0\", \"2.4.4\")), mdx(\"td\", _extends({\n    parentName: \"tr\"\n  }, {\n    \"align\": null\n  }), mdx(\"inlineCode\", {\n    parentName: \"td\"\n  }, \"design\")), mdx(\"td\", _extends({\n    parentName: \"tr\"\n  }, {\n    \"align\": null\n  }), mdx(\"inlineCode\", {\n    parentName: \"td\"\n  }, \"development\"))), mdx(\"tr\", {\n    parentName: \"tbody\"\n  }, mdx(\"td\", _extends({\n    parentName: \"tr\"\n  }, {\n    \"align\": null\n  }), \"Landmarks \\u2014 Use landmark roles to clearly identify regions that communicate page structure. If more than one landmark role occurs in the page, use aria-label to differentiate the landmark elements\"), mdx(\"td\", _extends({\n    parentName: \"tr\"\n  }, {\n    \"align\": null\n  }), mdx(\"a\", _extends({\n    parentName: \"td\"\n  }, {\n    \"href\": \"https://www.w3.org/TR/WCAG20-TECHS/ARIA11.html\"\n  }), \"ARIA11\")), mdx(\"td\", _extends({\n    parentName: \"tr\"\n  }, {\n    \"align\": null\n  }), mdx(\"inlineCode\", {\n    parentName: \"td\"\n  }, \"design\")), mdx(\"td\", _extends({\n    parentName: \"tr\"\n  }, {\n    \"align\": null\n  }), mdx(\"inlineCode\", {\n    parentName: \"td\"\n  }, \"development\"))), mdx(\"tr\", {\n    parentName: \"tbody\"\n  }, mdx(\"td\", _extends({\n    parentName: \"tr\"\n  }, {\n    \"align\": null\n  }), \"Headings \\u2014 Heading text should be descriptive. Correct heading levels should be used to communicate the outline of the page.\"), mdx(\"td\", _extends({\n    parentName: \"tr\"\n  }, {\n    \"align\": null\n  }), mdx(\"a\", _extends({\n    parentName: \"td\"\n  }, {\n    \"href\": \"https://www.w3.org/WAI/WCAG21/quickref/#section-headings\"\n  }), \"WCAG 2.4.10\"), \" and \", mdx(\"a\", _extends({\n    parentName: \"td\"\n  }, {\n    \"href\": \"https://www.w3.org/TR/WCAG20-TECHS/H42.html\"\n  }), \"H42\")), mdx(\"td\", _extends({\n    parentName: \"tr\"\n  }, {\n    \"align\": null\n  }), mdx(\"inlineCode\", {\n    parentName: \"td\"\n  }, \"design\")), mdx(\"td\", _extends({\n    parentName: \"tr\"\n  }, {\n    \"align\": null\n  }), mdx(\"inlineCode\", {\n    parentName: \"td\"\n  }, \"development\"))), mdx(\"tr\", {\n    parentName: \"tbody\"\n  }, mdx(\"td\", _extends({\n    parentName: \"tr\"\n  }, {\n    \"align\": null\n  }), \"Contents \\u2014 Should be meaningful, clear, and concise\"), mdx(\"td\", _extends({\n    parentName: \"tr\"\n  }, {\n    \"align\": null\n  })), mdx(\"td\", _extends({\n    parentName: \"tr\"\n  }, {\n    \"align\": null\n  }), mdx(\"inlineCode\", {\n    parentName: \"td\"\n  }, \"design\")), mdx(\"td\", _extends({\n    parentName: \"tr\"\n  }, {\n    \"align\": null\n  }))))), mdx(\"h2\", {\n    \"id\": \"guidelines-and-references\"\n  }, mdx(\"a\", _extends({\n    parentName: \"h2\"\n  }, {\n    \"href\": \"#guidelines-and-references\",\n    \"aria-label\": \"guidelines and references permalink\",\n    \"className\": \"anchor\"\n  }), mdx(\"svg\", _extends({\n    parentName: \"a\"\n  }, {\n    \"aria-hidden\": \"true\",\n    \"focusable\": \"false\",\n    \"height\": \"16\",\n    \"version\": \"1.1\",\n    \"viewBox\": \"0 0 16 16\",\n    \"width\": \"16\"\n  }), mdx(\"path\", _extends({\n    parentName: \"svg\"\n  }, {\n    \"fillRule\": \"evenodd\",\n    \"d\": \"M4 9h1v1H4c-1.5 0-3-1.69-3-3.5S2.55 3 4 3h4c1.45 0 3 1.69 3 3.5 0 1.41-.91 2.72-2 3.25V8.59c.58-.45 1-1.27 1-2.09C10 5.22 8.98 4 8 4H4c-.98 0-2 1.22-2 2.5S3 9 4 9zm9-3h-1v1h1c1 0 2 1.22 2 2.5S13.98 12 13 12H9c-.98 0-2-1.22-2-2.5 0-.83.42-1.64 1-2.09V6.25c-1.09.53-2 1.84-2 3.25C6 11.31 7.55 13 9 13h4c1.45 0 3-1.69 3-3.5S14.5 6 13 6z\"\n  })))), \"Guidelines and References\"), mdx(\"ul\", null, mdx(\"li\", {\n    parentName: \"ul\"\n  }, mdx(\"a\", _extends({\n    parentName: \"li\"\n  }, {\n    \"href\": \"https://www.w3.org/TR/WCAG21/\"\n  }), \"Web Content Accessibility Guidelines 2.1\")), mdx(\"li\", {\n    parentName: \"ul\"\n  }, mdx(\"a\", _extends({\n    parentName: \"li\"\n  }, {\n    \"href\": \"https://webaim.org/standards/wcag/checklist\"\n  }), \"WebAIM's WCAG 2.0 Checklist\")), mdx(\"li\", {\n    parentName: \"ul\"\n  }, mdx(\"a\", _extends({\n    parentName: \"li\"\n  }, {\n    \"href\": \"https://a11yproject.com/checklist\"\n  }), \"A11Y Project Checklist\"))), mdx(\"h3\", {\n    \"id\": \"patternfly-guidelines\"\n  }, mdx(\"a\", _extends({\n    parentName: \"h3\"\n  }, {\n    \"href\": \"#patternfly-guidelines\",\n    \"aria-label\": \"patternfly guidelines permalink\",\n    \"className\": \"anchor\"\n  }), mdx(\"svg\", _extends({\n    parentName: \"a\"\n  }, {\n    \"aria-hidden\": \"true\",\n    \"focusable\": \"false\",\n    \"height\": \"16\",\n    \"version\": \"1.1\",\n    \"viewBox\": \"0 0 16 16\",\n    \"width\": \"16\"\n  }), mdx(\"path\", _extends({\n    parentName: \"svg\"\n  }, {\n    \"fillRule\": \"evenodd\",\n    \"d\": \"M4 9h1v1H4c-1.5 0-3-1.69-3-3.5S2.55 3 4 3h4c1.45 0 3 1.69 3 3.5 0 1.41-.91 2.72-2 3.25V8.59c.58-.45 1-1.27 1-2.09C10 5.22 8.98 4 8 4H4c-.98 0-2 1.22-2 2.5S3 9 4 9zm9-3h-1v1h1c1 0 2 1.22 2 2.5S13.98 12 13 12H9c-.98 0-2-1.22-2-2.5 0-.83.42-1.64 1-2.09V6.25c-1.09.53-2 1.84-2 3.25C6 11.31 7.55 13 9 13h4c1.45 0 3-1.69 3-3.5S14.5 6 13 6z\"\n  })))), \"PatternFly Guidelines\"), mdx(\"p\", null, \"These are guidelines that we have defined for PatternFly.\"), mdx(\"h4\", {\n    \"id\": \"experience-parity\"\n  }, mdx(\"a\", _extends({\n    parentName: \"h4\"\n  }, {\n    \"href\": \"#experience-parity\",\n    \"aria-label\": \"experience parity permalink\",\n    \"className\": \"anchor\"\n  }), mdx(\"svg\", _extends({\n    parentName: \"a\"\n  }, {\n    \"aria-hidden\": \"true\",\n    \"focusable\": \"false\",\n    \"height\": \"16\",\n    \"version\": \"1.1\",\n    \"viewBox\": \"0 0 16 16\",\n    \"width\": \"16\"\n  }), mdx(\"path\", _extends({\n    parentName: \"svg\"\n  }, {\n    \"fillRule\": \"evenodd\",\n    \"d\": \"M4 9h1v1H4c-1.5 0-3-1.69-3-3.5S2.55 3 4 3h4c1.45 0 3 1.69 3 3.5 0 1.41-.91 2.72-2 3.25V8.59c.58-.45 1-1.27 1-2.09C10 5.22 8.98 4 8 4H4c-.98 0-2 1.22-2 2.5S3 9 4 9zm9-3h-1v1h1c1 0 2 1.22 2 2.5S13.98 12 13 12H9c-.98 0-2-1.22-2-2.5 0-.83.42-1.64 1-2.09V6.25c-1.09.53-2 1.84-2 3.25C6 11.31 7.55 13 9 13h4c1.45 0 3-1.69 3-3.5S14.5 6 13 6z\"\n  })))), \"Experience Parity\"), mdx(\"ul\", null, mdx(\"li\", {\n    parentName: \"ul\"\n  }, \"There should be parity between the screen reader contents and visibly rendered contents (refer to the \", mdx(\"a\", _extends({\n    parentName: \"li\"\n  }, {\n    \"href\": \"https://www.w3.org/TR/wai-aria/#aria-hidden\"\n  }), \"first Note for aria-hidden\"), \").\"), mdx(\"li\", {\n    parentName: \"ul\"\n  }, \"There should be parity among all input types: touch, mouse, and keyboard.\", mdx(\"ul\", {\n    parentName: \"li\"\n  }, mdx(\"li\", {\n    parentName: \"ul\"\n  }, \"Don\\u2019t optimize the experience for one input type at the expense of another.\"), mdx(\"li\", {\n    parentName: \"ul\"\n  }, \"Contents that a user can interact with using a mouse are also accessible using touch or keyboard.\"), mdx(\"li\", {\n    parentName: \"ul\"\n  }, \"Don\\u2019t show interactive elements on hover. Interactive elements that can display in a popup must display on click/touch/Enter events.\"))), mdx(\"li\", {\n    parentName: \"ul\"\n  }, \"There should be parity between hover and focus events.\", mdx(\"ul\", {\n    parentName: \"li\"\n  }, mdx(\"li\", {\n    parentName: \"ul\"\n  }, \"Any information that\\u2019s available on hover for the mouse user should be available on focus for the keyboard-only user, and also available to the screen reader user using \", mdx(\"inlineCode\", {\n    parentName: \"li\"\n  }, \"aria-describedby\"), \" (refer to \", mdx(\"a\", _extends({\n    parentName: \"li\"\n  }, {\n    \"href\": \"https://inclusive-components.design/tooltips-toggletips/\"\n  }), \"Tooltips & Toggletips example from Inclusive Components\"), \").\")))), mdx(\"h2\", {\n    \"id\": \"techniques\"\n  }, mdx(\"a\", _extends({\n    parentName: \"h2\"\n  }, {\n    \"href\": \"#techniques\",\n    \"aria-label\": \"techniques permalink\",\n    \"className\": \"anchor\"\n  }), mdx(\"svg\", _extends({\n    parentName: \"a\"\n  }, {\n    \"aria-hidden\": \"true\",\n    \"focusable\": \"false\",\n    \"height\": \"16\",\n    \"version\": \"1.1\",\n    \"viewBox\": \"0 0 16 16\",\n    \"width\": \"16\"\n  }), mdx(\"path\", _extends({\n    parentName: \"svg\"\n  }, {\n    \"fillRule\": \"evenodd\",\n    \"d\": \"M4 9h1v1H4c-1.5 0-3-1.69-3-3.5S2.55 3 4 3h4c1.45 0 3 1.69 3 3.5 0 1.41-.91 2.72-2 3.25V8.59c.58-.45 1-1.27 1-2.09C10 5.22 8.98 4 8 4H4c-.98 0-2 1.22-2 2.5S3 9 4 9zm9-3h-1v1h1c1 0 2 1.22 2 2.5S13.98 12 13 12H9c-.98 0-2-1.22-2-2.5 0-.83.42-1.64 1-2.09V6.25c-1.09.53-2 1.84-2 3.25C6 11.31 7.55 13 9 13h4c1.45 0 3-1.69 3-3.5S14.5 6 13 6z\"\n  })))), \"Techniques\"), mdx(\"p\", null, \"The \", mdx(\"a\", _extends({\n    parentName: \"p\"\n  }, {\n    \"href\": \"https://www.w3.org/TR/WCAG20-TECHS/Overview.html#contents\"\n  }), \"WCAG 2.0 techniques\"), \" provide examples on how to meet accessibility guidelines. Any techniques that are adopted as standard within PatternFly for handling specific patterns are included below.\"), mdx(\"h3\", {\n    \"id\": \"labels-and-accessible-names\"\n  }, mdx(\"a\", _extends({\n    parentName: \"h3\"\n  }, {\n    \"href\": \"#labels-and-accessible-names\",\n    \"aria-label\": \"labels and accessible names permalink\",\n    \"className\": \"anchor\"\n  }), mdx(\"svg\", _extends({\n    parentName: \"a\"\n  }, {\n    \"aria-hidden\": \"true\",\n    \"focusable\": \"false\",\n    \"height\": \"16\",\n    \"version\": \"1.1\",\n    \"viewBox\": \"0 0 16 16\",\n    \"width\": \"16\"\n  }), mdx(\"path\", _extends({\n    parentName: \"svg\"\n  }, {\n    \"fillRule\": \"evenodd\",\n    \"d\": \"M4 9h1v1H4c-1.5 0-3-1.69-3-3.5S2.55 3 4 3h4c1.45 0 3 1.69 3 3.5 0 1.41-.91 2.72-2 3.25V8.59c.58-.45 1-1.27 1-2.09C10 5.22 8.98 4 8 4H4c-.98 0-2 1.22-2 2.5S3 9 4 9zm9-3h-1v1h1c1 0 2 1.22 2 2.5S13.98 12 13 12H9c-.98 0-2-1.22-2-2.5 0-.83.42-1.64 1-2.09V6.25c-1.09.53-2 1.84-2 3.25C6 11.31 7.55 13 9 13h4c1.45 0 3-1.69 3-3.5S14.5 6 13 6z\"\n  })))), \"Labels and Accessible Names\"), mdx(\"ul\", null, mdx(\"li\", {\n    parentName: \"ul\"\n  }, mdx(\"h4\", _extends({\n    parentName: \"li\"\n  }, {\n    \"id\": \"form-fields\"\n  }), mdx(\"a\", _extends({\n    parentName: \"h4\"\n  }, {\n    \"href\": \"#form-fields\",\n    \"aria-label\": \"form fields permalink\",\n    \"className\": \"anchor\"\n  }), mdx(\"svg\", _extends({\n    parentName: \"a\"\n  }, {\n    \"aria-hidden\": \"true\",\n    \"focusable\": \"false\",\n    \"height\": \"16\",\n    \"version\": \"1.1\",\n    \"viewBox\": \"0 0 16 16\",\n    \"width\": \"16\"\n  }), mdx(\"path\", _extends({\n    parentName: \"svg\"\n  }, {\n    \"fillRule\": \"evenodd\",\n    \"d\": \"M4 9h1v1H4c-1.5 0-3-1.69-3-3.5S2.55 3 4 3h4c1.45 0 3 1.69 3 3.5 0 1.41-.91 2.72-2 3.25V8.59c.58-.45 1-1.27 1-2.09C10 5.22 8.98 4 8 4H4c-.98 0-2 1.22-2 2.5S3 9 4 9zm9-3h-1v1h1c1 0 2 1.22 2 2.5S13.98 12 13 12H9c-.98 0-2-1.22-2-2.5 0-.83.42-1.64 1-2.09V6.25c-1.09.53-2 1.84-2 3.25C6 11.31 7.55 13 9 13h4c1.45 0 3-1.69 3-3.5S14.5 6 13 6z\"\n  })))), \"Form Fields\"), mdx(\"ul\", {\n    parentName: \"li\"\n  }, mdx(\"li\", {\n    parentName: \"ul\"\n  }, \"Use explicit linking between \", mdx(\"inlineCode\", {\n    parentName: \"li\"\n  }, \"label\"), \" and form input elements (e.g. \", mdx(\"inlineCode\", {\n    parentName: \"li\"\n  }, \"input\"), \", \", mdx(\"inlineCode\", {\n    parentName: \"li\"\n  }, \"textarea\"), \", or \", mdx(\"inlineCode\", {\n    parentName: \"li\"\n  }, \"select\"), \") when both elements are present. Aside from providing an accessible name to screen readers, this method also increases the clickable area of the form element by making the label clickable, too. (\", mdx(\"a\", _extends({\n    parentName: \"li\"\n  }, {\n    \"href\": \"https://www.w3.org/TR/WCAG20-TECHS/H44.html\"\n  }), \"H44\"), \")\"), mdx(\"li\", {\n    parentName: \"ul\"\n  }, \"When a \", mdx(\"inlineCode\", {\n    parentName: \"li\"\n  }, \"label\"), \" element cannot accompany a form input element:\", mdx(\"ul\", {\n    parentName: \"li\"\n  }, mdx(\"li\", {\n    parentName: \"ul\"\n  }, \"Provide the label using \", mdx(\"inlineCode\", {\n    parentName: \"li\"\n  }, \"aria-label\"), \" or \", mdx(\"inlineCode\", {\n    parentName: \"li\"\n  }, \"aria-labelledby\"), \". (\", mdx(\"a\", _extends({\n    parentName: \"li\"\n  }, {\n    \"href\": \"https://www.w3.org/TR/WCAG20-TECHS/ARIA16.html\"\n  }), \"ARIA14\"), \")\"), mdx(\"li\", {\n    parentName: \"ul\"\n  }, \"In a single-field form, the submit button label can serve as the field label for sighted users (\", mdx(\"a\", _extends({\n    parentName: \"li\"\n  }, {\n    \"href\": \"https://www.w3.org/TR/WCAG20-TECHS/general.html#G167\"\n  }), \"G167\"), \") as well as assistive devices when using \", mdx(\"inlineCode\", {\n    parentName: \"li\"\n  }, \"aria-labelledby\")))))), mdx(\"li\", {\n    parentName: \"ul\"\n  }, mdx(\"h4\", _extends({\n    parentName: \"li\"\n  }, {\n    \"id\": \"landmark-roles\"\n  }), mdx(\"a\", _extends({\n    parentName: \"h4\"\n  }, {\n    \"href\": \"#landmark-roles\",\n    \"aria-label\": \"landmark roles permalink\",\n    \"className\": \"anchor\"\n  }), mdx(\"svg\", _extends({\n    parentName: \"a\"\n  }, {\n    \"aria-hidden\": \"true\",\n    \"focusable\": \"false\",\n    \"height\": \"16\",\n    \"version\": \"1.1\",\n    \"viewBox\": \"0 0 16 16\",\n    \"width\": \"16\"\n  }), mdx(\"path\", _extends({\n    parentName: \"svg\"\n  }, {\n    \"fillRule\": \"evenodd\",\n    \"d\": \"M4 9h1v1H4c-1.5 0-3-1.69-3-3.5S2.55 3 4 3h4c1.45 0 3 1.69 3 3.5 0 1.41-.91 2.72-2 3.25V8.59c.58-.45 1-1.27 1-2.09C10 5.22 8.98 4 8 4H4c-.98 0-2 1.22-2 2.5S3 9 4 9zm9-3h-1v1h1c1 0 2 1.22 2 2.5S13.98 12 13 12H9c-.98 0-2-1.22-2-2.5 0-.83.42-1.64 1-2.09V6.25c-1.09.53-2 1.84-2 3.25C6 11.31 7.55 13 9 13h4c1.45 0 3-1.69 3-3.5S14.5 6 13 6z\"\n  })))), \"Landmark Roles\"), mdx(\"ul\", {\n    parentName: \"li\"\n  }, mdx(\"li\", {\n    parentName: \"ul\"\n  }, \"Screen reader users can navigate to sections of a page when \", mdx(\"a\", _extends({\n    parentName: \"li\"\n  }, {\n    \"href\": \"https://www.w3.org/TR/wai-aria-1.1/#landmark_roles\"\n  }), \"landmark roles\"), \" are used. Whenever a landmark role is used more than once, provide a name using \", mdx(\"inlineCode\", {\n    parentName: \"li\"\n  }, \"aria-label\"), \" or \", mdx(\"inlineCode\", {\n    parentName: \"li\"\n  }, \"aria-labelledby\"), \" to provide context for that landmark. (\", mdx(\"a\", _extends({\n    parentName: \"li\"\n  }, {\n    \"href\": \"https://www.w3.org/TR/WCAG20-TECHS/ARIA6.html\"\n  }), \"ARIA6\"), \", \", mdx(\"a\", _extends({\n    parentName: \"li\"\n  }, {\n    \"href\": \"https://www.w3.org/TR/WCAG20-TECHS/ARIA16.html\"\n  }), \"ARIA16\"), \")\"), mdx(\"li\", {\n    parentName: \"ul\"\n  }, \"While \", mdx(\"a\", _extends({\n    parentName: \"li\"\n  }, {\n    \"href\": \"https://www.w3.org/TR/wai-aria-1.1/#toolbar\"\n  }), mdx(\"inlineCode\", {\n    parentName: \"a\"\n  }, \"toolbar\")), \" is not a landmark role, the same rule applies to this role.\"))), mdx(\"li\", {\n    parentName: \"ul\"\n  }, mdx(\"h4\", _extends({\n    parentName: \"li\"\n  }, {\n    \"id\": \"icons\"\n  }), mdx(\"a\", _extends({\n    parentName: \"h4\"\n  }, {\n    \"href\": \"#icons\",\n    \"aria-label\": \"icons permalink\",\n    \"className\": \"anchor\"\n  }), mdx(\"svg\", _extends({\n    parentName: \"a\"\n  }, {\n    \"aria-hidden\": \"true\",\n    \"focusable\": \"false\",\n    \"height\": \"16\",\n    \"version\": \"1.1\",\n    \"viewBox\": \"0 0 16 16\",\n    \"width\": \"16\"\n  }), mdx(\"path\", _extends({\n    parentName: \"svg\"\n  }, {\n    \"fillRule\": \"evenodd\",\n    \"d\": \"M4 9h1v1H4c-1.5 0-3-1.69-3-3.5S2.55 3 4 3h4c1.45 0 3 1.69 3 3.5 0 1.41-.91 2.72-2 3.25V8.59c.58-.45 1-1.27 1-2.09C10 5.22 8.98 4 8 4H4c-.98 0-2 1.22-2 2.5S3 9 4 9zm9-3h-1v1h1c1 0 2 1.22 2 2.5S13.98 12 13 12H9c-.98 0-2-1.22-2-2.5 0-.83.42-1.64 1-2.09V6.25c-1.09.53-2 1.84-2 3.25C6 11.31 7.55 13 9 13h4c1.45 0 3-1.69 3-3.5S14.5 6 13 6z\"\n  })))), \"Icons\"), mdx(\"p\", {\n    parentName: \"li\"\n  }, \"Icons can either be decorative or semantic. Icons are \", mdx(\"strong\", {\n    parentName: \"p\"\n  }, \"decorative\"), \" if you can remove an icon without affecting the information that is presented on the page. Icons are \", mdx(\"strong\", {\n    parentName: \"p\"\n  }, \"semantic\"), \" when they provide information that otherwise isn't present, such as indicating status, indicating type of alert message, or replacing text as button labels. When an icon is semantic, the meaning must be provided in alternative ways to the user. The following guidelines should be followed when using icons within PatternFly components.\"), mdx(\"ul\", {\n    parentName: \"li\"\n  }, mdx(\"li\", {\n    parentName: \"ul\"\n  }, mdx(\"p\", {\n    parentName: \"li\"\n  }, \"Add \", mdx(\"inlineCode\", {\n    parentName: \"p\"\n  }, \"aria-hidden=\\\"true\\\"\"), \" for all icons, either to the icon element or a parent element of the icon. This renders the icon as something that assistive devices can ignore.\")), mdx(\"li\", {\n    parentName: \"ul\"\n  }, mdx(\"p\", {\n    parentName: \"li\"\n  }, \"Additionally, for \", mdx(\"strong\", {\n    parentName: \"p\"\n  }, \"semantic\"), \" icons:\"), mdx(\"ul\", {\n    parentName: \"li\"\n  }, mdx(\"li\", {\n    parentName: \"ul\"\n  }, mdx(\"p\", {\n    parentName: \"li\"\n  }, \"Add a label for the icon in tooltip text that displays on hover, and also on focus for focusable elements.\")), mdx(\"li\", {\n    parentName: \"ul\"\n  }, mdx(\"p\", {\n    parentName: \"li\"\n  }, \"For interactive elements like \", mdx(\"inlineCode\", {\n    parentName: \"p\"\n  }, \"<a>\"), \" and \", mdx(\"inlineCode\", {\n    parentName: \"p\"\n  }, \"<button>\"), \" where an icon is used as the label instead of text, provide the label on the interactive element using \", mdx(\"inlineCode\", {\n    parentName: \"p\"\n  }, \"aria-label\"), \". For example:\"), mdx(\"pre\", {\n    parentName: \"li\"\n  }, mdx(\"code\", _extends({\n    parentName: \"pre\"\n  }, {\n    \"className\": \"language-html\"\n  }), \"<button class=\\\"...\\\" aria-label=\\\"Close Dialog\\\">\\n  <i class=\\\"...\\\" aria-hidden=\\\"true\\\"></i>\\n</button>\\n\"))), mdx(\"li\", {\n    parentName: \"ul\"\n  }, mdx(\"p\", {\n    parentName: \"li\"\n  }, \"For non-interactive icons, include \", mdx(\"inlineCode\", {\n    parentName: \"p\"\n  }, \".pf-screen-reader\"), \" text near the icon. Depending on the component, the \", mdx(\"inlineCode\", {\n    parentName: \"p\"\n  }, \".pf-screen-reader\"), \" text might not be a direct sibling to the icon element. For example, in the Alert component, the icon label text is adjacent to the message. This way, when \", mdx(\"inlineCode\", {\n    parentName: \"p\"\n  }, \"role=\\\"alert\\\"\"), \" is added to \", mdx(\"inlineCode\", {\n    parentName: \"p\"\n  }, \".pf-c-alert__body\"), \" for dynamically displayed alerts, the type of message is announced along with the message text.\"), mdx(\"pre\", {\n    parentName: \"li\"\n  }, mdx(\"code\", _extends({\n    parentName: \"pre\"\n  }, {\n    \"className\": \"language-html\"\n  }), \"<div class=\\\"pf-c-alert pf-m-success\\\" aria-label=\\\"Success Alert\\\">\\n  <div aria-hidden=\\\"true\\\" class=\\\"pf-c-alert__icon\\\">\\n    <i class=\\\"fas fa-check-circle\\\"></i>\\n  </div>\\n  <div class=\\\"pf-c-alert__body\\\">\\n    <h4 class=\\\"pf-c-alert__title\\\">\\n      {{#> screen-reader}}Success:{{/screen-reader}} Success alert title\\n    </h4>\\n  </div>\\n</div>\\n\")))))))), mdx(\"h3\", {\n    \"id\": \"trapping-focus\"\n  }, mdx(\"a\", _extends({\n    parentName: \"h3\"\n  }, {\n    \"href\": \"#trapping-focus\",\n    \"aria-label\": \"trapping focus permalink\",\n    \"className\": \"anchor\"\n  }), mdx(\"svg\", _extends({\n    parentName: \"a\"\n  }, {\n    \"aria-hidden\": \"true\",\n    \"focusable\": \"false\",\n    \"height\": \"16\",\n    \"version\": \"1.1\",\n    \"viewBox\": \"0 0 16 16\",\n    \"width\": \"16\"\n  }), mdx(\"path\", _extends({\n    parentName: \"svg\"\n  }, {\n    \"fillRule\": \"evenodd\",\n    \"d\": \"M4 9h1v1H4c-1.5 0-3-1.69-3-3.5S2.55 3 4 3h4c1.45 0 3 1.69 3 3.5 0 1.41-.91 2.72-2 3.25V8.59c.58-.45 1-1.27 1-2.09C10 5.22 8.98 4 8 4H4c-.98 0-2 1.22-2 2.5S3 9 4 9zm9-3h-1v1h1c1 0 2 1.22 2 2.5S13.98 12 13 12H9c-.98 0-2-1.22-2-2.5 0-.83.42-1.64 1-2.09V6.25c-1.09.53-2 1.84-2 3.25C6 11.31 7.55 13 9 13h4c1.45 0 3-1.69 3-3.5S14.5 6 13 6z\"\n  })))), \"Trapping Focus\"), mdx(\"p\", null, \"The recommended interaction pattern for the modal components like the Modal or Popover is to trap focus within the modal element of the component when it becomes visible. For keyboard-only users that use the Tab key to navigate the interface, this means that focus cannot be shifted outside of the modal when using the Tab key. Instead, when focus leaves the last focusable item, it should be placed on the first focusable item of the modal. For screen reader users, the other contents on the page should be hidden from the screen reader.\"), mdx(\"p\", null, \"The method we recommend \", mdx(\"a\", _extends({\n    parentName: \"p\"\n  }, {\n    \"href\": \"#testing\"\n  }), \"based on the screen reader / browser combinations we use for testing\"), \" is to apply \", mdx(\"inlineCode\", {\n    parentName: \"p\"\n  }, \"aria-hidden=\\\"true\\\"\"), \" to the parent wrapping element of the page contents. Note that the modal element of the component must not be a descendent of this element with \", mdx(\"inlineCode\", {\n    parentName: \"p\"\n  }, \"aria-hidden=\\\"true\\\"\"), \" and should be included as a sibling to this element.\"), mdx(\"h2\", {\n    \"id\": \"testing\"\n  }, mdx(\"a\", _extends({\n    parentName: \"h2\"\n  }, {\n    \"href\": \"#testing\",\n    \"aria-label\": \"testing permalink\",\n    \"className\": \"anchor\"\n  }), mdx(\"svg\", _extends({\n    parentName: \"a\"\n  }, {\n    \"aria-hidden\": \"true\",\n    \"focusable\": \"false\",\n    \"height\": \"16\",\n    \"version\": \"1.1\",\n    \"viewBox\": \"0 0 16 16\",\n    \"width\": \"16\"\n  }), mdx(\"path\", _extends({\n    parentName: \"svg\"\n  }, {\n    \"fillRule\": \"evenodd\",\n    \"d\": \"M4 9h1v1H4c-1.5 0-3-1.69-3-3.5S2.55 3 4 3h4c1.45 0 3 1.69 3 3.5 0 1.41-.91 2.72-2 3.25V8.59c.58-.45 1-1.27 1-2.09C10 5.22 8.98 4 8 4H4c-.98 0-2 1.22-2 2.5S3 9 4 9zm9-3h-1v1h1c1 0 2 1.22 2 2.5S13.98 12 13 12H9c-.98 0-2-1.22-2-2.5 0-.83.42-1.64 1-2.09V6.25c-1.09.53-2 1.84-2 3.25C6 11.31 7.55 13 9 13h4c1.45 0 3-1.69 3-3.5S14.5 6 13 6z\"\n  })))), \"Testing\"), mdx(\"p\", null, \"Many accessibility issues can be found by doing a few simple checks:\"), mdx(\"ol\", null, mdx(\"li\", {\n    parentName: \"ol\"\n  }, \"Use an accessibility audit tool to check for violations. If you are using PatternFly in your project, we recommend using \", mdx(\"a\", _extends({\n    parentName: \"li\"\n  }, {\n    \"href\": \"https://www.deque.com/axe/\"\n  }), \"aXe: The Accessibility Engine\"), \" to check for accessibility violations. If you are contributing to PatternFly, refer to our \", mdx(\"a\", _extends({\n    parentName: \"li\"\n  }, {\n    \"href\": \"https://github.com/patternfly/patternfly-next/blob/master/README.md#testing-for-accessibility\"\n  }), \"README.md\"), \" on how to run this tool.\"), mdx(\"li\", {\n    parentName: \"ol\"\n  }, \"Test keyboard accessibility, and check that these requirements are met:\", mdx(\"ul\", {\n    parentName: \"li\"\n  }, mdx(\"li\", {\n    parentName: \"ul\"\n  }, \"All functionality is keyboard accessible\"), mdx(\"li\", {\n    parentName: \"ul\"\n  }, \"Order of elements in the HTML and in the layout follow a logical order\"), mdx(\"li\", {\n    parentName: \"ul\"\n  }, \"Elements with focus are clearly visible\"))), mdx(\"li\", {\n    parentName: \"ol\"\n  }, \"Disable styles, then test the information architecture and presence of adequate text labels. The \", mdx(\"a\", _extends({\n    parentName: \"li\"\n  }, {\n    \"href\": \"https://wave.webaim.org/extension/\"\n  }), \"WAVE browser extension from WebAIM\"), \" provides this feature if it isn't available in the browser you are using.\"), mdx(\"li\", {\n    parentName: \"ol\"\n  }, \"Test with any screen reader available in your operating system. Screen readers that we target for testing PatternFly are:\", mdx(\"ul\", {\n    parentName: \"li\"\n  }, mdx(\"li\", {\n    parentName: \"ul\"\n  }, \"JAWS with Chrome, Windows (\", mdx(\"a\", _extends({\n    parentName: \"li\"\n  }, {\n    \"href\": \"https://dequeuniversity.com/screenreaders/jaws-keyboard-shortcuts\"\n  }), \"keyboard shortcuts\"), \")\"), mdx(\"li\", {\n    parentName: \"ul\"\n  }, \"Voiceover with Safari, Mac (\", mdx(\"a\", _extends({\n    parentName: \"li\"\n  }, {\n    \"href\": \"https://dequeuniversity.com/screenreaders/voiceover-keyboard-shortcuts\"\n  }), \"keyboard shortcuts\"), \")\"), mdx(\"li\", {\n    parentName: \"ul\"\n  }, \"NVDA with Firefox, Windows (\", mdx(\"a\", _extends({\n    parentName: \"li\"\n  }, {\n    \"href\": \"https://dequeuniversity.com/screenreaders/nvda-keyboard-shortcuts\"\n  }), \"keyboard shortcuts\"), \")\"))), mdx(\"li\", {\n    parentName: \"ol\"\n  }, \"Check color contrast for:\", mdx(\"ul\", {\n    parentName: \"li\"\n  }, mdx(\"li\", {\n    parentName: \"ul\"\n  }, \"Text color against background color (\", mdx(\"a\", _extends({\n    parentName: \"li\"\n  }, {\n    \"href\": \"https://www.w3.org/WAI/WCAG21/Understanding/contrast-minimum.html\"\n  }), \"Understanding WCAG 1.4.3\"), \")\"), mdx(\"li\", {\n    parentName: \"ul\"\n  }, \"Text color against link color (\", mdx(\"a\", _extends({\n    parentName: \"li\"\n  }, {\n    \"href\": \"https://www.w3.org/TR/WCAG20-TECHS/G183.html\"\n  }), \"Technique G183\"), \")\"), mdx(\"li\", {\n    parentName: \"ul\"\n  }, \"Visible boundaries of buttons and form elements against adjacent background color (\", mdx(\"a\", _extends({\n    parentName: \"li\"\n  }, {\n    \"href\": \"https://www.w3.org/WAI/WCAG21/Understanding/non-text-contrast.html\"\n  }), \"Understanding WCAG 1.4.11\"), \")\")))));\n}\nMDXContent.isMDXComponent = true;"},"frontmatter":{"path":"/get-started/accessibility-guide"}},"allGetStartedNavigationJson":{"edges":[{"node":{"text":"About","path":"/get-started/about"}},{"node":{"text":"Develop","path":"/get-started/developers"}},{"node":{"text":"Design","path":"/get-started/designers"}},{"node":{"text":"Migration guide","path":"/get-started/migrate"}},{"node":{"text":"Accessibility guide","path":"/get-started/accessibility-guide"}}]},"allDesignGuidelinesNavigationJson":{"edges":[{"node":{"text":"Styles","path":"/design-guidelines/styles/","subNav":[{"text":"Colors","path":"/design-guidelines/styles/colors"},{"text":"Colors for charts","path":"/design-guidelines/styles/colors-for-charts"},{"text":"Icons","path":"/design-guidelines/styles/icons"},{"text":"Typography","path":"/design-guidelines/styles/typography"},{"text":"Spacers","path":"/design-guidelines/styles/spacers"}]}},{"node":{"text":"Usage and behavior","path":"/design-guidelines/usage-and-behavior/","subNav":[{"text":"About modal","path":"/design-guidelines/usage-and-behavior/about-modal"},{"text":"Alerts and notifications","path":"/design-guidelines/usage-and-behavior/alerts-and-notifications"},{"text":"Buttons and links","path":"/design-guidelines/usage-and-behavior/buttons-and-links"},{"text":"Charts","path":"/design-guidelines/usage-and-behavior/charts"},{"text":"Data input","path":"/design-guidelines/usage-and-behavior/data-input"},{"text":"Empty state","path":"/design-guidelines/usage-and-behavior/empty-state"},{"text":"Filters","path":"/design-guidelines/usage-and-behavior/filters"},{"text":"Forms","path":"/design-guidelines/usage-and-behavior/forms"},{"text":"Lists and tables","path":"/design-guidelines/usage-and-behavior/lists-and-tables"},{"text":"Login","path":"/design-guidelines/usage-and-behavior/login"},{"text":"Modal dialog","path":"/design-guidelines/usage-and-behavior/modal"},{"text":"Navigation system","path":"/design-guidelines/usage-and-behavior/navigation-system"},{"text":"Progress bar","path":"/design-guidelines/usage-and-behavior/progress-bar"},{"text":"Toolbar","path":"/design-guidelines/usage-and-behavior/toolbar"},{"text":"Wizard","path":"/design-guidelines/usage-and-behavior/wizard"}]}},{"node":{"text":"Content","path":"/design-guidelines/content","subNav":[{"text":"Writing","path":"/design-guidelines/content/writing"},{"text":"Voice","path":"/design-guidelines/content/voice-and-tone"},{"text":"Style guide","path":"/design-guidelines/content/grammar-and-terminology"}]}}]},"allContributeNavigationJson":{"edges":[{"node":{"text":"About","path":"/contribute/about"}},{"node":{"text":"Develop","path":"/contribute/developers"}},{"node":{"text":"Design","path":"/contribute/designers"}}]}},"pageContext":{}}